pantheon_cli/__init__.py
pantheon_cli/cli/__init__.py
pantheon_cli/cli/__main__.py
pantheon_cli/cli/core.py
pantheon_cli/cli/manager/api_key_manager.py
pantheon_cli/cli/manager/model_manager.py
pantheon_cli/cli/prompt/atac_bulk_upstream.py
pantheon_cli/cli/prompt/atac_sc_upstream.py
pantheon_cli/cli/prompt/dock_interactive.py
pantheon_cli/cli/prompt/dock_molecular.py
pantheon_cli/cli/prompt/hic_analysis.py
pantheon_cli/cli/prompt/rna_bulk_upstream.py
pantheon_cli/cli/prompt/scatac_analysis.py
pantheon_cli/cli/prompt/scrna_anno_analysis.py
pantheon_cli/cli/prompt/scrna_anno_analysis_old.py
pantheon_cli/cli/prompt/scrna_cci_analysis.py
pantheon_cli/cli/prompt/scrna_subtype_analysis.py
pantheon_cli/cli/prompt/spatial_bin2cell.py
pantheon_cli/repl/__init__.py
pantheon_cli/repl/__main__.py
pantheon_cli/repl/bio_handler.py
pantheon_cli/repl/core.py
pantheon_cli/repl/team.py
pantheon_cli/repl/ui.py
pantheon_cli/utils/__init__.py
pantheon_cli/utils/config_loader.py
pantheon_cli/utils/display.py
pantheon_cli-0.1.3.dist-info/METADATA
pantheon_cli-0.1.3.dist-info/WHEEL
pantheon_cli-0.1.3.dist-info/entry_points.txt
pantheon_cli-0.1.3.dist-info/top_level.txt
pantheon_cli-0.1.3.dist-info/RECORD
