Metadata-Version: 2.4
Name: pantheon-cli
Version: 0.1.3
Summary: Command Line Interface for Pantheon - A framework for building distributed evolvable multi-agent systems.
Requires-Python: >=3.10
Requires-Dist: pantheon-agents>=0.3.2
Requires-Dist: pantheon-toolsets>=0.5.3
Requires-Dist: fire>=0.7.0
Requires-Dist: rich>=13.9.4
Requires-Dist: rich-pyfiglet
Requires-Dist: hypha_rpc
Requires-Dist: pandas
Provides-Extra: dev
Requires-Dist: pytest>=8.3.4; extra == "dev"
Requires-Dist: pytest-asyncio>=0.25.0; extra == "dev"
